griffe_inherited_method_crossrefs/__init__.py
griffe_inherited_method_crossrefs-0.0.1.4.dist-info/METADATA
griffe_inherited_method_crossrefs-0.0.1.4.dist-info/WHEEL
griffe_inherited_method_crossrefs-0.0.1.4.dist-info/licenses/LICENSE
griffe_inherited_method_crossrefs-0.0.1.4.dist-info/RECORD
