Metadata-Version: 2.1
Name: griffe-inherited-method-crossrefs
Version: 0.0.1.4
Summary: Griffe extension to replace docstrings of inherited methods with cross-references to parent
Project-URL: Repository, https://github.com/mlprt/griffe-inherited-method-crossrefs
Author-email: Matt Laporte <matt.l.laporte@gmail.com>
License: 				Apache License
License-File: LICENSE
Classifier: Development Status :: 3 - Alpha
Classifier: Intended Audience :: Developers
Classifier: Programming Language :: Python
Classifier: Programming Language :: Python :: 3
Classifier: Programming Language :: Python :: 3 :: Only
Classifier: Programming Language :: Python :: 3.8
Classifier: Programming Language :: Python :: 3.9
Classifier: Programming Language :: Python :: 3.10
Classifier: Programming Language :: Python :: 3.11
Classifier: Programming Language :: Python :: 3.12
Classifier: Topic :: Documentation
Classifier: Topic :: Software Development
Classifier: Topic :: Utilities
Classifier: Typing :: Typed
Requires-Python: >=3.9
Requires-Dist: griffe>=0.38
